EasyEnc/__init__.py
EasyEnc/classes.py
easyenc-0.0.2.dist-info/LICENSE.txt
easyenc-0.0.2.dist-info/METADATA
easyenc-0.0.2.dist-info/WHEEL
easyenc-0.0.2.dist-info/top_level.txt
easyenc-0.0.2.dist-info/RECORD
