Metadata-Version: 2.1
Name: easyenc
Version: 0.0.2
Summary: An easy encryption module.
Home-page: https://github.com/dsnk24/easy-enc
Author: dsnk
Author-email: erick.8bld@gmail.com
License: UNKNOWN
Platform: UNKNOWN
Classifier: Programming Language :: Python :: 3
Classifier: License :: OSI Approved :: MIT License
Classifier: Operating System :: OS Independent
Requires-Python: >=3.6
